sysall/SysAll.py
sysall/__init__.py
sysall-1.1.14.dist-info/LICENSE
sysall-1.1.14.dist-info/METADATA
sysall-1.1.14.dist-info/WHEEL
sysall-1.1.14.dist-info/top_level.txt
sysall-1.1.14.dist-info/RECORD
