Metadata-Version: 2.1
Name: sysall
Version: 1.1.14
Summary: Tools to facilitate the use/manipulation of data in the Windows environment
Home-page: https://github.com/LixNew2/SysAll
Author: LixNew
Author-email: lixnew12@gmail.com
Classifier: Programming Language :: Python :: 3
Classifier: License :: OSI Approved :: MIT License
Classifier: Operating System :: OS Independent
Requires-Python: >=3.7
License-File: LICENSE
Requires-Dist: WMI
Requires-Dist: getmac
Requires-Dist: psutil
Requires-Dist: py-cpuinfo
Requires-Dist: requests
